{
  "slices": {
    "Hero": {
      "default": {
        "primary": {
          "text": {
            "config": {
              "patternType": "STORY",
              "blocks": 1
            }
          }
        }
      }
    },
    "Text": {
      "default": {
        "primary": {
          "text": {
            "config": {
              "patternType": "PARAGRAPH",
              "blocks": 4
            }
          }
        }
      }
    },
    "Image": {
      "default": {
        "primary": {}
      },
      "banner": {
        "primary": {}
      }
    },
    "Quote": {
      "default": {
        "primary": {
          "quote": {
            "config": {
              "patternType": "HEADING",
              "blocks": 1
            }
          }
        }
      }
    },
    "TextWithImage": {
      "default": {
        "primary": {
          "text": {
            "config": {
              "patternType": "STORY",
              "blocks": 1
            }
          },
          "image": {
            "content": "https://images.prismic.io/nextjs-starter-prismic-multi-page/fcb2333d-d2b2-4cdc-acdd-f9558703472d_anders-jilden-Sc5RKXLBjGg-unsplash.jpg"
          }
        }
      },
      "withButton": {
        "primary": {
          "text": {
            "config": {
              "patternType": "PARAGRAPH",
              "blocks": 1
            }
          }
        }
      }
    },
    "ImageCards": {
      "default": {
        "primary": {
          "heading": {
            "config": {
              "patternType": "HEADING",
              "blocks": 1
            }
          }
        },
        "items": {}
      }
    },
    "MainImage": {
      "3366": {
        "primary": {
          "dimentions": {
            "config": {
              "patternType": "PARAGRAPH",
              "blocks": 1
            }
          },
          "dimentions2": {
            "config": {
              "patternType": "PARAGRAPH",
              "blocks": 1
            }
          }
        },
        "items": {}
      },
      "4060": {
        "primary": {
          "dimentions": {
            "config": {
              "patternType": "PARAGRAPH",
              "blocks": 1
            }
          },
          "dimentions2": {
            "config": {
              "patternType": "PARAGRAPH",
              "blocks": 1
            }
          }
        },
        "items": {}
      },
      "5050": {
        "primary": {
          "dimentions": {
            "config": {
              "patternType": "PARAGRAPH",
              "blocks": 1
            }
          },
          "dimentions2": {
            "config": {
              "patternType": "PARAGRAPH",
              "blocks": 1
            }
          },
          "dimentions3": {
            "config": {
              "patternType": "PARAGRAPH",
              "blocks": 1
            }
          }
        },
        "items": {}
      },
      "6040": {
        "primary": {
          "dimentions": {
            "config": {
              "patternType": "PARAGRAPH",
              "blocks": 1
            }
          },
          "dimentions2": {
            "config": {
              "patternType": "PARAGRAPH",
              "blocks": 1
            }
          }
        },
        "items": {}
      },
      "333333": {
        "primary": {
          "dimentions": {
            "config": {
              "patternType": "PARAGRAPH",
              "blocks": 1
            }
          },
          "dimentions2": {
            "config": {
              "patternType": "PARAGRAPH",
              "blocks": 1
            }
          },
          "dimentions3": {
            "config": {
              "patternType": "PARAGRAPH",
              "blocks": 1
            }
          }
        },
        "items": {}
      },
      "default": {
        "primary": {
          "title": {
            "config": {
              "patternType": "PARAGRAPH",
              "blocks": 1
            }
          },
          "dimentions": {
            "config": {
              "patternType": "PARAGRAPH",
              "blocks": 1
            }
          }
        },
        "items": {}
      }
    },
    "Project": {
      "default": {
        "primary": {
          "namedateyear": {
            "config": {
              "patternType": "PARAGRAPH",
              "blocks": 1
            }
          },
          "description": {
            "config": {
              "patternType": "PARAGRAPH",
              "blocks": 1
            }
          }
        }
      }
    },
    "About": {
      "default": {
        "primary": {}
      },
      "image": {
        "primary": {},
        "items": {}
      },
      "datedText": {
        "items": {},
        "primary": {}
      }
    },
    "AboutImage": {
      "default": {
        "primary": {}
      }
    },
    "AboutText": {
      "default": {
        "primary": {},
        "items": {}
      },
      "date": {
        "items": {
          "text": {
            "config": {
              "patternType": "PARAGRAPH",
              "blocks": 1
            }
          }
        },
        "primary": {
          "title": {
            "config": {
              "patternType": "PARAGRAPH",
              "blocks": 1
            }
          }
        }
      }
    },
    "AboutInfo": {
      "default": {
        "primary": {},
        "items": {}
      }
    },
    "EnlargedSlider": {
      "default": {
        "primary": {},
        "items": {
          "materials": {
            "config": {
              "patternType": "PARAGRAPH",
              "blocks": 1
            }
          }
        }
      }
    },
    "ContactInfo": {
      "default": {
        "primary": {
          "title": {
            "config": {
              "patternType": "PARAGRAPH",
              "blocks": 1
            }
          }
        },
        "items": {}
      }
    },
    "Education": {
      "default": {
        "primary": {}
      }
    },
    "Collections": {
      "default": {
        "primary": {},
        "items": {
          "text": {
            "config": {
              "patternType": "PARAGRAPH",
              "blocks": 1
            }
          }
        }
      }
    },
    "Bibliography": {
      "default": {
        "primary": {},
        "items": {
          "text": {
            "config": {
              "patternType": "PARAGRAPH",
              "blocks": 1
            }
          }
        }
      }
    },
    "Exhibitions": {
      "default": {
        "items": {
          "title": {
            "config": {
              "patternType": "PARAGRAPH",
              "blocks": 1
            }
          }
        },
        "primary": {}
      }
    },
    "Residencies": {
      "default": {
        "primary": {},
        "items": {
          "title": {
            "config": {
              "patternType": "PARAGRAPH",
              "blocks": 1
            }
          }
        }
      }
    }
  },
  "_cts": {
    "page": {
      "title": {
        "config": {
          "patternType": "HEADING",
          "blocks": 1
        }
      }
    },
    "navigation": {},
    "settings": {},
    "enlarged": {}
  }
}